sideko_portal/__init__.py
sideko_portal/client.py
sideko_portal/core/__init__.py
sideko_portal/core/api_error.py
sideko_portal/core/auth.py
sideko_portal/core/base_client.py
sideko_portal/core/binary_response.py
sideko_portal/core/query.py
sideko_portal/core/request.py
sideko_portal/core/response.py
sideko_portal/core/type_utils.py
sideko_portal/core/utils.py
sideko_portal/environment.py
sideko_portal/resources/api/README.md
sideko_portal/resources/api/__init__.py
sideko_portal/resources/api/client.py
sideko_portal/resources/api/spec/README.md
sideko_portal/resources/api/spec/__init__.py
sideko_portal/resources/api/spec/client.py
sideko_portal/resources/api_link/README.md
sideko_portal/resources/api_link/__init__.py
sideko_portal/resources/api_link/client.py
sideko_portal/resources/api_link/group/README.md
sideko_portal/resources/api_link/group/__init__.py
sideko_portal/resources/api_link/group/client.py
sideko_portal/resources/asset/README.md
sideko_portal/resources/asset/__init__.py
sideko_portal/resources/asset/client.py
sideko_portal/resources/auth/README.md
sideko_portal/resources/auth/__init__.py
sideko_portal/resources/auth/client.py
sideko_portal/resources/cli/README.md
sideko_portal/resources/cli/__init__.py
sideko_portal/resources/cli/client.py
sideko_portal/resources/doc/README.md
sideko_portal/resources/doc/__init__.py
sideko_portal/resources/doc/client.py
sideko_portal/resources/doc/deployment/README.md
sideko_portal/resources/doc/deployment/__init__.py
sideko_portal/resources/doc/deployment/client.py
sideko_portal/resources/doc/preview/README.md
sideko_portal/resources/doc/preview/__init__.py
sideko_portal/resources/doc/preview/client.py
sideko_portal/resources/doc/theme/README.md
sideko_portal/resources/doc/theme/__init__.py
sideko_portal/resources/doc/theme/client.py
sideko_portal/resources/doc/version/README.md
sideko_portal/resources/doc/version/__init__.py
sideko_portal/resources/doc/version/client.py
sideko_portal-0.3.2.dist-info/METADATA
sideko_portal-0.3.2.dist-info/WHEEL
sideko_portal-0.3.2.dist-info/RECORD
